{"u":"http://www.juntadeandalucia.es/medioambiente/atmosfera/informes_siva/mar14/ma140330.htm","time":1396137600,"stations":[{"t":"CAMPILLOS","s":"CAMPILLOS","so2":0,"co":0,"no2":2,"part":0,"o3":3,"g":3,"prev":3,"act":3,"evol":1,"gs":{"p":"MALAGA","t":"CAMPILLOS","s":"CAMPILLOS","addr":"PASEO DE PEARROLLA, CARRETERA CAMPILLOS MLAGA KM 1","gsd":[{"time":1396134600,"so2":8,"part":47,"no2":0,"co":0,"o3":0},{"time":1396135200,"so2":8,"part":42,"no2":0,"co":0,"o3":0},{"time":1396135800,"so2":7,"part":42,"no2":0,"co":0,"o3":0},{"time":1396136400,"so2":6,"part":46,"no2":0,"co":0,"o3":0},{"time":1396137000,"so2":6,"part":50,"no2":0,"co":0,"o3":0},{"time":1396137600,"so2":5,"part":50,"no2":0,"co":0,"o3":0},{"time":1396138200,"so2":5,"part":46,"no2":0,"co":0,"o3":0},{"time":1396138800,"so2":5,"part":43,"no2":0,"co":0,"o3":0},{"time":1396139400,"so2":6,"part":39,"no2":0,"co":0,"o3":0},{"time":1396140000,"so2":5,"part":47,"no2":0,"co":0,"o3":0},{"time":1396140600,"so2":5,"part":50,"no2":0,"co":0,"o3":0},{"time":1396141200,"so2":5,"part":52,"no2":0,"co":0,"o3":0},{"time":1396141800,"so2":5,"part":44,"no2":0,"co":0,"o3":0},{"time":1396142400,"so2":5,"part":44,"no2":0,"co":0,"o3":0},{"time":1396143000,"so2":5,"part":41,"no2":0,"co":0,"o3":0},{"time":1396143600,"so2":5,"part":34,"no2":0,"co":0,"o3":0},{"time":1396144200,"so2":4,"part":36,"no2":0,"co":0,"o3":0},{"time":1396144800,"so2":5,"part":39,"no2":0,"co":0,"o3":0},{"time":1396145400,"so2":5,"part":41,"no2":0,"co":0,"o3":0},{"time":1396146000,"so2":5,"part":44,"no2":0,"co":0,"o3":0},{"time":1396146600,"so2":5,"part":43,"no2":0,"co":0,"o3":0},{"time":1396147200,"so2":4,"part":37,"no2":0,"co":0,"o3":0},{"time":1396147800,"so2":4,"part":35,"no2":0,"co":0,"o3":0},{"time":1396148400,"so2":4,"part":35,"no2":0,"co":0,"o3":0},{"time":1396149000,"so2":4,"part":39,"no2":0,"co":0,"o3":0},{"time":1396149600,"so2":5,"part":37,"no2":0,"co":0,"o3":0},{"time":1396150200,"so2":5,"part":34,"no2":0,"co":0,"o3":0},{"time":1396150800,"so2":5,"part":39,"no2":0,"co":0,"o3":0},{"time":1396151400,"so2":4,"part":37,"no2":0,"co":0,"o3":0},{"time":1396152000,"so2":4,"part":36,"no2":0,"co":0,"o3":0},{"time":1396152600,"so2":4,"part":34,"no2":0,"co":0,"o3":0},{"time":1396153200,"so2":4,"part":36,"no2":0,"co":0,"o3":0},{"time":1396153800,"so2":4,"part":37,"no2":0,"co":0,"o3":0},{"time":1396154400,"so2":5,"part":40,"no2":0,"co":0,"o3":0},{"time":1396155000,"so2":4,"part":39,"no2":0,"co":0,"o3":0},{"time":1396155600,"so2":4,"part":31,"no2":0,"co":0,"o3":0},{"time":1396156200,"so2":6,"part":29,"no2":0,"co":0,"o3":0},{"time":1396156800,"so2":7,"part":29,"no2":0,"co":0,"o3":0},{"time":1396157400,"so2":5,"part":33,"no2":0,"co":0,"o3":0},{"time":1396158000,"so2":6,"part":33,"no2":0,"co":0,"o3":0},{"time":1396158600,"so2":6,"part":30,"no2":0,"co":0,"o3":0},{"time":1396159200,"so2":7,"part":29,"no2":0,"co":0,"o3":0},{"time":1396159800,"so2":6,"part":33,"no2":0,"co":0,"o3":0},{"time":1396160400,"so2":6,"part":34,"no2":0,"co":0,"o3":0},{"time":1396161000,"so2":4,"part":48,"no2":0,"co":0,"o3":0},{"time":1396161600,"so2":2,"part":54,"no2":0,"co":0,"o3":0},{"time":1396162200,"so2":3,"part":39,"no2":0,"co":0,"o3":0},{"time":1396162800,"so2":3,"part":31,"no2":0,"co":0,"o3":0},{"time":1396163400,"so2":4,"part":32,"no2":0,"co":0,"o3":0},{"time":1396164000,"so2":4,"part":33,"no2":0,"co":0,"o3":0},{"time":1396164600,"so2":4,"part":35,"no2":0,"co":0,"o3":0},{"time":1396165200,"so2":4,"part":39,"no2":0,"co":0,"o3":0},{"time":1396165800,"so2":4,"part":44,"no2":0,"co":0,"o3":0},{"time":1396166400,"so2":4,"part":49,"no2":0,"co":0,"o3":0},{"time":1396167000,"so2":3,"part":56,"no2":0,"co":0,"o3":0},{"time":1396167600,"so2":3,"part":55,"no2":0,"co":0,"o3":0},{"time":1396168200,"so2":3,"part":59,"no2":0,"co":0,"o3":0},{"time":1396168800,"so2":4,"part":63,"no2":0,"co":0,"o3":0},{"time":1396169400,"so2":4,"part":65,"no2":0,"co":0,"o3":0},{"time":1396170000,"so2":4,"part":72,"no2":0,"co":0,"o3":0},{"time":1396170600,"so2":4,"part":84,"no2":0,"co":0,"o3":0},{"time":1396171200,"so2":4,"part":87,"no2":0,"co":0,"o3":0},{"time":1396171800,"so2":3,"part":91,"no2":0,"co":0,"o3":0},{"time":1396172400,"so2":4,"part":95,"no2":0,"co":0,"o3":0},{"time":1396173000,"so2":4,"part":99,"no2":0,"co":0,"o3":0},{"time":1396173600,"so2":4,"part":100,"no2":0,"co":0,"o3":0},{"time":1396174200,"so2":4,"part":102,"no2":0,"co":0,"o3":0},{"time":1396174800,"so2":4,"part":103,"no2":0,"co":0,"o3":0},{"time":1396175400,"so2":4,"part":105,"no2":0,"co":0,"o3":0},{"time":1396176000,"so2":4,"part":105,"no2":0,"co":0,"o3":0},{"time":1396176600,"so2":4,"part":105,"no2":0,"co":0,"o3":0},{"time":1396177200,"so2":5,"part":105,"no2":0,"co":0,"o3":0},{"time":1396177800,"so2":5,"part":106,"no2":0,"co":0,"o3":0},{"time":1396178400,"so2":4,"part":107,"no2":0,"co":0,"o3":0},{"time":1396179000,"so2":5,"part":108,"no2":0,"co":0,"o3":0},{"time":1396179600,"so2":5,"part":108,"no2":0,"co":0,"o3":0},{"time":1396180200,"so2":5,"part":109,"no2":0,"co":0,"o3":0},{"time":1396180800,"so2":5,"part":109,"no2":0,"co":0,"o3":0},{"time":1396181400,"so2":6,"part":108,"no2":0,"co":0,"o3":0},{"time":1396182000,"so2":5,"part":108,"no2":0,"co":0,"o3":0},{"time":1396182600,"so2":5,"part":108,"no2":0,"co":0,"o3":0},{"time":1396183200,"so2":5,"part":108,"no2":0,"co":0,"o3":0},{"time":1396183800,"so2":5,"part":108,"no2":0,"co":0,"o3":0},{"time":1396184400,"so2":6,"part":106,"no2":0,"co":0,"o3":0},{"time":1396185000,"so2":6,"part":106,"no2":0,"co":0,"o3":0},{"time":1396185600,"so2":6,"part":105,"no2":0,"co":0,"o3":0},{"time":1396186200,"so2":6,"part":106,"no2":0,"co":0,"o3":0},{"time":1396186800,"so2":5,"part":105,"no2":0,"co":0,"o3":0},{"time":1396187400,"so2":5,"part":105,"no2":0,"co":0,"o3":0},{"time":1396188000,"so2":5,"part":104,"no2":0,"co":0,"o3":0},{"time":1396188600,"so2":5,"part":104,"no2":0,"co":0,"o3":0},{"time":1396189200,"so2":5,"part":105,"no2":0,"co":0,"o3":0},{"time":1396189800,"so2":5,"part":105,"no2":0,"co":0,"o3":0},{"time":1396190400,"so2":5,"part":105,"no2":0,"co":0,"o3":0},{"time":1396191000,"so2":5,"part":105,"no2":0,"co":0,"o3":0},{"time":1396191600,"so2":5,"part":105,"no2":0,"co":0,"o3":0},{"time":1396192200,"so2":5,"part":105,"no2":0,"co":0,"o3":0},{"time":1396192800,"so2":5,"part":105,"no2":0,"co":0,"o3":0},{"time":1396193400,"so2":5,"part":105,"no2":0,"co":0,"o3":0},{"time":1396194000,"so2":5,"part":104,"no2":0,"co":0,"o3":0},{"time":1396194600,"so2":5,"part":103,"no2":0,"co":0,"o3":0},{"time":1396195200,"so2":6,"part":103,"no2":0,"co":0,"o3":0},{"time":1396195800,"so2":6,"part":102,"no2":0,"co":0,"o3":0},{"time":1396196400,"so2":6,"part":101,"no2":0,"co":0,"o3":0},{"time":1396197000,"so2":5,"part":102,"no2":0,"co":0,"o3":0},{"time":1396197600,"so2":5,"part":101,"no2":0,"co":0,"o3":0},{"time":1396198200,"so2":5,"part":99,"no2":0,"co":0,"o3":0},{"time":1396198800,"so2":6,"part":97,"no2":0,"co":0,"o3":0},{"time":1396199400,"so2":6,"part":95,"no2":0,"co":0,"o3":0},{"time":1396200000,"so2":6,"part":95,"no2":0,"co":0,"o3":0},{"time":1396200600,"so2":5,"part":96,"no2":0,"co":0,"o3":0},{"time":1396201200,"so2":5,"part":97,"no2":0,"co":0,"o3":0},{"time":1396201800,"so2":5,"part":95,"no2":0,"co":0,"o3":0},{"time":1396202400,"so2":5,"part":94,"no2":0,"co":0,"o3":0},{"time":1396203000,"so2":6,"part":92,"no2":0,"co":0,"o3":0},{"time":1396203600,"so2":6,"part":90,"no2":0,"co":0,"o3":0},{"time":1396204200,"so2":7,"part":89,"no2":0,"co":0,"o3":0},{"time":1396204800,"so2":7,"part":90,"no2":0,"co":0,"o3":0},{"time":1396205400,"so2":6,"part":90,"no2":0,"co":0,"o3":0},{"time":1396206000,"so2":7,"part":89,"no2":0,"co":0,"o3":0},{"time":1396206600,"so2":7,"part":86,"no2":0,"co":0,"o3":0},{"time":1396207200,"so2":7,"part":86,"no2":0,"co":0,"o3":0},{"time":1396207800,"so2":7,"part":89,"no2":0,"co":0,"o3":0},{"time":1396208400,"so2":6,"part":89,"no2":0,"co":0,"o3":0},{"time":1396209000,"so2":6,"part":89,"no2":0,"co":0,"o3":0},{"time":1396209600,"so2":6,"part":88,"no2":0,"co":0,"o3":0},{"time":1396210200,"so2":6,"part":91,"no2":0,"co":0,"o3":0},{"time":1396210800,"so2":6,"part":91,"no2":0,"co":0,"o3":0},{"time":1396211400,"so2":5,"part":93,"no2":0,"co":0,"o3":0},{"time":1396212000,"so2":5,"part":93,"no2":0,"co":0,"o3":0},{"time":1396212600,"so2":4,"part":94,"no2":0,"co":0,"o3":0},{"time":1396213200,"so2":4,"part":93,"no2":0,"co":0,"o3":0},{"time":1396213800,"so2":5,"part":91,"no2":0,"co":0,"o3":0},{"time":1396214400,"so2":5,"part":90,"no2":0,"co":0,"o3":0},{"time":1396215000,"so2":5,"part":88,"no2":0,"co":0,"o3":0},{"time":1396215600,"so2":5,"part":87,"no2":0,"co":0,"o3":0},{"time":1396216200,"so2":5,"part":88,"no2":0,"co":0,"o3":0},{"time":1396216800,"so2":5,"part":87,"no2":0,"co":0,"o3":0}]}},{"t":"MALAGA","s":"AVENIDA JUAN XXIII","so2":0,"co":0,"no2":3,"part":0,"o3":0,"g":3,"prev":3,"act":3,"evol":1,"gs":{"p":"MALAGA","t":"MALAGA","s":"AVENIDA JUAN XXIII","addr":"AVENIDA JUAN XXIII","gsd":[{"time":1396134600,"so2":104,"part":0,"no2":0,"co":0,"o3":0},{"time":1396135200,"so2":100,"part":0,"no2":0,"co":0,"o3":0},{"time":1396135800,"so2":111,"part":0,"no2":0,"co":0,"o3":0},{"time":1396136400,"so2":114,"part":0,"no2":0,"co":0,"o3":0},{"time":1396137000,"so2":107,"part":0,"no2":0,"co":0,"o3":0},{"time":1396137600,"so2":105,"part":0,"no2":0,"co":0,"o3":0},{"time":1396138200,"so2":112,"part":0,"no2":0,"co":0,"o3":0},{"time":1396138800,"so2":108,"part":0,"no2":0,"co":0,"o3":0},{"time":1396139400,"so2":111,"part":0,"no2":0,"co":0,"o3":0},{"time":1396140000,"so2":98,"part":0,"no2":0,"co":0,"o3":0},{"time":1396140600,"so2":89,"part":0,"no2":0,"co":0,"o3":0},{"time":1396141200,"so2":94,"part":0,"no2":0,"co":0,"o3":0},{"time":1396141800,"so2":85,"part":0,"no2":0,"co":0,"o3":0},{"time":1396142400,"so2":87,"part":0,"no2":0,"co":0,"o3":0},{"time":1396143000,"so2":85,"part":0,"no2":0,"co":0,"o3":0},{"time":1396143600,"so2":88,"part":0,"no2":0,"co":0,"o3":0},{"time":1396144200,"so2":70,"part":0,"no2":0,"co":0,"o3":0},{"time":1396144800,"so2":74,"part":0,"no2":0,"co":0,"o3":0},{"time":1396145400,"so2":77,"part":0,"no2":0,"co":0,"o3":0},{"time":1396146000,"so2":68,"part":0,"no2":0,"co":0,"o3":0},{"time":1396146600,"so2":41,"part":0,"no2":0,"co":0,"o3":0},{"time":1396147200,"so2":41,"part":0,"no2":0,"co":0,"o3":0},{"time":1396147800,"so2":75,"part":0,"no2":0,"co":0,"o3":0},{"time":1396148400,"so2":73,"part":0,"no2":0,"co":0,"o3":0},{"time":1396149000,"so2":55,"part":0,"no2":0,"co":0,"o3":0},{"time":1396149600,"so2":26,"part":0,"no2":0,"co":0,"o3":0},{"time":1396150200,"so2":38,"part":0,"no2":0,"co":0,"o3":0},{"time":1396150800,"so2":28,"part":0,"no2":0,"co":0,"o3":0},{"time":1396151400,"so2":38,"part":0,"no2":0,"co":0,"o3":0},{"time":1396152000,"so2":40,"part":0,"no2":0,"co":0,"o3":0},{"time":1396152600,"so2":29,"part":0,"no2":0,"co":0,"o3":0},{"time":1396153200,"so2":27,"part":0,"no2":0,"co":0,"o3":0},{"time":1396153800,"so2":19,"part":0,"no2":0,"co":0,"o3":0},{"time":1396154400,"so2":28,"part":0,"no2":0,"co":0,"o3":0},{"time":1396155000,"so2":44,"part":0,"no2":0,"co":0,"o3":0},{"time":1396155600,"so2":42,"part":0,"no2":0,"co":0,"o3":0},{"time":1396156200,"so2":45,"part":0,"no2":0,"co":0,"o3":0},{"time":1396156800,"so2":42,"part":0,"no2":0,"co":0,"o3":0},{"time":1396157400,"so2":50,"part":0,"no2":0,"co":0,"o3":0},{"time":1396158000,"so2":24,"part":0,"no2":0,"co":0,"o3":0},{"time":1396158600,"so2":27,"part":0,"no2":0,"co":0,"o3":0},{"time":1396159200,"so2":25,"part":0,"no2":0,"co":0,"o3":0},{"time":1396159800,"so2":22,"part":0,"no2":0,"co":0,"o3":0},{"time":1396160400,"so2":22,"part":0,"no2":0,"co":0,"o3":0},{"time":1396161000,"so2":25,"part":0,"no2":0,"co":0,"o3":0},{"time":1396161600,"so2":25,"part":0,"no2":0,"co":0,"o3":0},{"time":1396162200,"so2":16,"part":0,"no2":0,"co":0,"o3":0},{"time":1396162800,"so2":17,"part":0,"no2":0,"co":0,"o3":0},{"time":1396163400,"so2":30,"part":0,"no2":0,"co":0,"o3":0},{"time":1396164000,"so2":24,"part":0,"no2":0,"co":0,"o3":0},{"time":1396164600,"so2":10,"part":0,"no2":0,"co":0,"o3":0},{"time":1396165200,"so2":9,"part":0,"no2":0,"co":0,"o3":0},{"time":1396165800,"so2":15,"part":0,"no2":0,"co":0,"o3":0},{"time":1396166400,"so2":22,"part":0,"no2":0,"co":0,"o3":0},{"time":1396167000,"so2":11,"part":0,"no2":0,"co":0,"o3":0},{"time":1396167600,"so2":32,"part":0,"no2":0,"co":0,"o3":0},{"time":1396168200,"so2":12,"part":0,"no2":0,"co":0,"o3":0},{"time":1396168800,"so2":7,"part":0,"no2":0,"co":0,"o3":0},{"time":1396169400,"so2":23,"part":0,"no2":0,"co":0,"o3":0},{"time":1396170000,"so2":27,"part":0,"no2":0,"co":0,"o3":0},{"time":1396170600,"so2":28,"part":0,"no2":0,"co":0,"o3":0},{"time":1396171200,"so2":21,"part":0,"no2":0,"co":0,"o3":0},{"time":1396171800,"so2":36,"part":0,"no2":0,"co":0,"o3":0},{"time":1396172400,"so2":36,"part":0,"no2":0,"co":0,"o3":0},{"time":1396173000,"so2":26,"part":0,"no2":0,"co":0,"o3":0},{"time":1396173600,"so2":25,"part":0,"no2":0,"co":0,"o3":0},{"time":1396174200,"so2":22,"part":0,"no2":0,"co":0,"o3":0},{"time":1396174800,"so2":18,"part":0,"no2":0,"co":0,"o3":0},{"time":1396175400,"so2":14,"part":0,"no2":0,"co":0,"o3":0},{"time":1396176000,"so2":25,"part":0,"no2":0,"co":0,"o3":0},{"time":1396176600,"so2":36,"part":0,"no2":0,"co":0,"o3":0},{"time":1396177200,"so2":31,"part":0,"no2":0,"co":0,"o3":0},{"time":1396177800,"so2":28,"part":0,"no2":0,"co":0,"o3":0},{"time":1396178400,"so2":26,"part":0,"no2":0,"co":0,"o3":0},{"time":1396179000,"so2":29,"part":0,"no2":0,"co":0,"o3":0},{"time":1396179600,"so2":29,"part":0,"no2":0,"co":0,"o3":0},{"time":1396180200,"so2":24,"part":0,"no2":0,"co":0,"o3":0},{"time":1396180800,"so2":29,"part":0,"no2":0,"co":0,"o3":0},{"time":1396181400,"so2":6,"part":0,"no2":0,"co":0,"o3":0},{"time":1396182000,"so2":13,"part":0,"no2":0,"co":0,"o3":0},{"time":1396182600,"so2":22,"part":0,"no2":0,"co":0,"o3":0},{"time":1396183200,"so2":42,"part":0,"no2":0,"co":0,"o3":0},{"time":1396183800,"so2":54,"part":0,"no2":0,"co":0,"o3":0},{"time":1396184400,"so2":29,"part":0,"no2":0,"co":0,"o3":0},{"time":1396185000,"so2":24,"part":0,"no2":0,"co":0,"o3":0},{"time":1396185600,"so2":23,"part":0,"no2":0,"co":0,"o3":0},{"time":1396186200,"so2":20,"part":0,"no2":0,"co":0,"o3":0},{"time":1396186800,"so2":13,"part":0,"no2":0,"co":0,"o3":0},{"time":1396187400,"so2":34,"part":0,"no2":0,"co":0,"o3":0},{"time":1396188000,"so2":19,"part":0,"no2":0,"co":0,"o3":0},{"time":1396188600,"so2":22,"part":0,"no2":0,"co":0,"o3":0},{"time":1396189200,"so2":28,"part":0,"no2":0,"co":0,"o3":0},{"time":1396189800,"so2":21,"part":0,"no2":0,"co":0,"o3":0},{"time":1396190400,"so2":47,"part":0,"no2":0,"co":0,"o3":0},{"time":1396191000,"so2":41,"part":0,"no2":0,"co":0,"o3":0},{"time":1396191600,"so2":43,"part":0,"no2":0,"co":0,"o3":0},{"time":1396192200,"so2":36,"part":0,"no2":0,"co":0,"o3":0},{"time":1396192800,"so2":46,"part":0,"no2":0,"co":0,"o3":0},{"time":1396193400,"so2":38,"part":0,"no2":0,"co":0,"o3":0},{"time":1396194000,"so2":42,"part":0,"no2":0,"co":0,"o3":0},{"time":1396194600,"so2":32,"part":0,"no2":0,"co":0,"o3":0},{"time":1396195200,"so2":27,"part":0,"no2":0,"co":0,"o3":0},{"time":1396195800,"so2":44,"part":0,"no2":0,"co":0,"o3":0},{"time":1396196400,"so2":39,"part":0,"no2":0,"co":0,"o3":0},{"time":1396197000,"so2":41,"part":0,"no2":0,"co":0,"o3":0},{"time":1396197600,"so2":26,"part":0,"no2":0,"co":0,"o3":0},{"time":1396198200,"so2":41,"part":0,"no2":0,"co":0,"o3":0},{"time":1396198800,"so2":39,"part":0,"no2":0,"co":0,"o3":0},{"time":1396199400,"so2":36,"part":0,"no2":0,"co":0,"o3":0},{"time":1396200000,"so2":35,"part":0,"no2":0,"co":0,"o3":0},{"time":1396200600,"so2":53,"part":0,"no2":0,"co":0,"o3":0},{"time":1396201200,"so2":40,"part":0,"no2":0,"co":0,"o3":0},{"time":1396201800,"so2":22,"part":0,"no2":0,"co":0,"o3":0},{"time":1396202400,"so2":33,"part":0,"no2":0,"co":0,"o3":0},{"time":1396203000,"so2":32,"part":0,"no2":0,"co":0,"o3":0},{"time":1396203600,"so2":57,"part":0,"no2":0,"co":0,"o3":0},{"time":1396204200,"so2":34,"part":0,"no2":0,"co":0,"o3":0},{"time":1396204800,"so2":56,"part":0,"no2":0,"co":0,"o3":0},{"time":1396205400,"so2":32,"part":0,"no2":0,"co":0,"o3":0},{"time":1396206000,"so2":40,"part":0,"no2":0,"co":0,"o3":0},{"time":1396206600,"so2":42,"part":0,"no2":0,"co":0,"o3":0},{"time":1396207200,"so2":78,"part":0,"no2":0,"co":0,"o3":0},{"time":1396207800,"so2":56,"part":0,"no2":0,"co":0,"o3":0},{"time":1396208400,"so2":78,"part":0,"no2":0,"co":0,"o3":0},{"time":1396209000,"so2":109,"part":0,"no2":0,"co":0,"o3":0},{"time":1396209600,"so2":112,"part":0,"no2":0,"co":0,"o3":0},{"time":1396210200,"so2":107,"part":0,"no2":0,"co":0,"o3":0},{"time":1396210800,"so2":127,"part":0,"no2":0,"co":0,"o3":0},{"time":1396211400,"so2":131,"part":0,"no2":0,"co":0,"o3":0},{"time":1396212000,"so2":143,"part":0,"no2":0,"co":0,"o3":0},{"time":1396212600,"so2":119,"part":0,"no2":0,"co":0,"o3":0},{"time":1396213200,"so2":99,"part":0,"no2":0,"co":0,"o3":0},{"time":1396213800,"so2":94,"part":0,"no2":0,"co":0,"o3":0},{"time":1396214400,"so2":56,"part":0,"no2":0,"co":0,"o3":0},{"time":1396215000,"so2":95,"part":0,"no2":0,"co":0,"o3":0},{"time":1396215600,"so2":74,"part":0,"no2":0,"co":0,"o3":0},{"time":1396216200,"so2":67,"part":0,"no2":0,"co":0,"o3":0},{"time":1396216800,"so2":70,"part":0,"no2":0,"co":0,"o3":0}]}},{"t":"MALAGA","s":"CAMPANILLAS","so2":2,"co":2,"no2":1,"part":2,"o3":3,"g":3,"prev":3,"act":3,"evol":1,"gs":{"p":"MALAGA","t":"MALAGA","s":"CAMPANILLAS","addr":"FINCA LA LIRA, CARRETERA C\ufffdRTAMA KM 12","gsd":[{"time":1396134600,"so2":6,"part":11,"no2":0,"co":96,"o3":59},{"time":1396135200,"so2":6,"part":11,"no2":0,"co":122,"o3":49},{"time":1396135800,"so2":6,"part":11,"no2":0,"co":135,"o3":47},{"time":1396136400,"so2":6,"part":11,"no2":0,"co":133,"o3":47},{"time":1396137000,"so2":6,"part":11,"no2":0,"co":136,"o3":43},{"time":1396137600,"so2":6,"part":11,"no2":0,"co":148,"o3":37},{"time":1396138200,"so2":5,"part":13,"no2":0,"co":139,"o3":43},{"time":1396138800,"so2":5,"part":14,"no2":0,"co":110,"o3":51},{"time":1396139400,"so2":5,"part":14,"no2":0,"co":91,"o3":54},{"time":1396140000,"so2":6,"part":14,"no2":0,"co":103,"o3":49},{"time":1396140600,"so2":6,"part":14,"no2":0,"co":98,"o3":49},{"time":1396141200,"so2":5,"part":14,"no2":0,"co":100,"o3":48},{"time":1396141800,"so2":5,"part":14,"no2":0,"co":98,"o3":55},{"time":1396142400,"so2":5,"part":14,"no2":0,"co":105,"o3":59},{"time":1396143000,"so2":5,"part":14,"no2":0,"co":92,"o3":57},{"time":1396143600,"so2":5,"part":14,"no2":0,"co":90,"o3":58},{"time":1396144200,"so2":5,"part":14,"no2":0,"co":96,"o3":57},{"time":1396144800,"so2":5,"part":14,"no2":0,"co":97,"o3":54},{"time":1396145400,"so2":5,"part":9,"no2":0,"co":102,"o3":50},{"time":1396146000,"so2":7,"part":9,"no2":0,"co":94,"o3":41},{"time":1396146600,"so2":7,"part":9,"no2":0,"co":99,"o3":25},{"time":1396147200,"so2":7,"part":9,"no2":0,"co":100,"o3":23},{"time":1396147800,"so2":7,"part":9,"no2":0,"co":98,"o3":28},{"time":1396148400,"so2":7,"part":9,"no2":0,"co":92,"o3":30},{"time":1396149000,"so2":7,"part":15,"no2":0,"co":101,"o3":33},{"time":1396149600,"so2":8,"part":16,"no2":0,"co":93,"o3":34},{"time":1396150200,"so2":7,"part":16,"no2":0,"co":96,"o3":32},{"time":1396150800,"so2":7,"part":15,"no2":0,"co":97,"o3":34},{"time":1396151400,"so2":7,"part":15,"no2":0,"co":94,"o3":34},{"time":1396152000,"so2":8,"part":16,"no2":0,"co":101,"o3":36},{"time":1396152600,"so2":7,"part":18,"no2":0,"co":98,"o3":37},{"time":1396153200,"so2":7,"part":18,"no2":0,"co":96,"o3":38},{"time":1396153800,"so2":7,"part":18,"no2":0,"co":99,"o3":41},{"time":1396154400,"so2":7,"part":18,"no2":0,"co":97,"o3":41},{"time":1396155000,"so2":7,"part":18,"no2":0,"co":92,"o3":43},{"time":1396155600,"so2":7,"part":18,"no2":0,"co":72,"o3":40},{"time":1396156200,"so2":7,"part":15,"no2":0,"co":56,"o3":42},{"time":1396156800,"so2":7,"part":15,"no2":0,"co":55,"o3":43},{"time":1396157400,"so2":7,"part":16,"no2":0,"co":56,"o3":42},{"time":1396158000,"so2":7,"part":16,"no2":0,"co":56,"o3":41},{"time":1396158600,"so2":7,"part":16,"no2":0,"co":52,"o3":41},{"time":1396159200,"so2":7,"part":15,"no2":0,"co":58,"o3":42},{"time":1396159800,"so2":7,"part":10,"no2":0,"co":52,"o3":42},{"time":1396160400,"so2":7,"part":10,"no2":0,"co":50,"o3":42},{"time":1396161000,"so2":7,"part":10,"no2":0,"co":49,"o3":39},{"time":1396161600,"so2":7,"part":11,"no2":0,"co":48,"o3":31},{"time":1396162200,"so2":7,"part":10,"no2":0,"co":56,"o3":36},{"time":1396162800,"so2":7,"part":10,"no2":0,"co":48,"o3":42},{"time":1396163400,"so2":7,"part":13,"no2":0,"co":52,"o3":44},{"time":1396164000,"so2":7,"part":13,"no2":0,"co":50,"o3":47},{"time":1396164600,"so2":7,"part":13,"no2":0,"co":54,"o3":49},{"time":1396165200,"so2":7,"part":13,"no2":0,"co":50,"o3":47},{"time":1396165800,"so2":7,"part":13,"no2":0,"co":52,"o3":49},{"time":1396166400,"so2":7,"part":13,"no2":0,"co":59,"o3":49},{"time":1396167000,"so2":7,"part":14,"no2":0,"co":59,"o3":49},{"time":1396167600,"so2":8,"part":14,"no2":0,"co":72,"o3":51},{"time":1396168200,"so2":8,"part":14,"no2":0,"co":98,"o3":54},{"time":1396168800,"so2":7,"part":14,"no2":0,"co":90,"o3":58},{"time":1396169400,"so2":7,"part":14,"no2":0,"co":66,"o3":63},{"time":1396170000,"so2":7,"part":14,"no2":0,"co":55,"o3":67},{"time":1396170600,"so2":6,"part":16,"no2":0,"co":53,"o3":71},{"time":1396171200,"so2":6,"part":16,"no2":0,"co":56,"o3":82},{"time":1396171800,"so2":7,"part":16,"no2":0,"co":52,"o3":88},{"time":1396172400,"so2":6,"part":16,"no2":0,"co":46,"o3":85},{"time":1396173000,"so2":7,"part":16,"no2":0,"co":59,"o3":90},{"time":1396173600,"so2":7,"part":16,"no2":0,"co":42,"o3":91},{"time":1396174200,"so2":6,"part":5,"no2":0,"co":44,"o3":92},{"time":1396174800,"so2":7,"part":6,"no2":0,"co":48,"o3":91},{"time":1396175400,"so2":6,"part":6,"no2":0,"co":49,"o3":90},{"time":1396176000,"so2":6,"part":5,"no2":0,"co":50,"o3":89},{"time":1396176600,"so2":6,"part":6,"no2":0,"co":48,"o3":91},{"time":1396177200,"so2":6,"part":6,"no2":0,"co":44,"o3":91},{"time":1396177800,"so2":6,"part":9,"no2":0,"co":47,"o3":91},{"time":1396178400,"so2":6,"part":9,"no2":0,"co":44,"o3":92},{"time":1396179000,"so2":6,"part":9,"no2":0,"co":50,"o3":93},{"time":1396179600,"so2":6,"part":9,"no2":0,"co":42,"o3":93},{"time":1396180200,"so2":6,"part":9,"no2":0,"co":43,"o3":93},{"time":1396180800,"so2":6,"part":9,"no2":0,"co":41,"o3":94},{"time":1396181400,"so2":6,"part":11,"no2":0,"co":53,"o3":94},{"time":1396182000,"so2":6,"part":11,"no2":0,"co":46,"o3":94},{"time":1396182600,"so2":6,"part":11,"no2":0,"co":39,"o3":94},{"time":1396183200,"so2":6,"part":11,"no2":0,"co":49,"o3":95},{"time":1396183800,"so2":6,"part":11,"no2":0,"co":46,"o3":96},{"time":1396184400,"so2":6,"part":11,"no2":0,"co":45,"o3":96},{"time":1396185000,"so2":6,"part":10,"no2":0,"co":49,"o3":97},{"time":1396185600,"so2":6,"part":11,"no2":0,"co":37,"o3":97},{"time":1396186200,"so2":6,"part":10,"no2":0,"co":45,"o3":96},{"time":1396186800,"so2":6,"part":10,"no2":0,"co":43,"o3":97},{"time":1396187400,"so2":6,"part":10,"no2":0,"co":48,"o3":97},{"time":1396188000,"so2":6,"part":10,"no2":0,"co":52,"o3":97},{"time":1396188600,"so2":6,"part":10,"no2":0,"co":44,"o3":95},{"time":1396189200,"so2":6,"part":10,"no2":0,"co":48,"o3":94},{"time":1396189800,"so2":6,"part":10,"no2":0,"co":56,"o3":93},{"time":1396190400,"so2":6,"part":10,"no2":0,"co":37,"o3":95},{"time":1396191000,"so2":6,"part":10,"no2":0,"co":48,"o3":96},{"time":1396191600,"so2":6,"part":10,"no2":0,"co":57,"o3":93},{"time":1396192200,"so2":6,"part":8,"no2":0,"co":48,"o3":93},{"time":1396192800,"so2":6,"part":8,"no2":0,"co":49,"o3":94},{"time":1396193400,"so2":6,"part":8,"no2":0,"co":46,"o3":94},{"time":1396194000,"so2":6,"part":8,"no2":0,"co":46,"o3":92},{"time":1396194600,"so2":7,"part":8,"no2":0,"co":57,"o3":92},{"time":1396195200,"so2":6,"part":7,"no2":0,"co":52,"o3":91},{"time":1396195800,"so2":7,"part":6,"no2":0,"co":55,"o3":92},{"time":1396196400,"so2":6,"part":6,"no2":0,"co":44,"o3":92},{"time":1396197000,"so2":6,"part":6,"no2":0,"co":51,"o3":91},{"time":1396197600,"so2":6,"part":6,"no2":0,"co":46,"o3":92},{"time":1396198200,"so2":6,"part":6,"no2":0,"co":58,"o3":90},{"time":1396198800,"so2":6,"part":6,"no2":0,"co":48,"o3":87},{"time":1396199400,"so2":6,"part":5,"no2":0,"co":50,"o3":86},{"time":1396200000,"so2":7,"part":5,"no2":0,"co":54,"o3":84},{"time":1396200600,"so2":7,"part":5,"no2":0,"co":42,"o3":82},{"time":1396201200,"so2":6,"part":5,"no2":0,"co":49,"o3":79},{"time":1396201800,"so2":7,"part":5,"no2":0,"co":53,"o3":77},{"time":1396202400,"so2":6,"part":5,"no2":0,"co":58,"o3":76},{"time":1396203000,"so2":6,"part":19,"no2":0,"co":49,"o3":76},{"time":1396203600,"so2":6,"part":19,"no2":0,"co":63,"o3":78},{"time":1396204200,"so2":6,"part":19,"no2":0,"co":89,"o3":78},{"time":1396204800,"so2":6,"part":19,"no2":0,"co":88,"o3":72},{"time":1396205400,"so2":7,"part":19,"no2":0,"co":92,"o3":70},{"time":1396206000,"so2":7,"part":19,"no2":0,"co":101,"o3":70},{"time":1396206600,"so2":6,"part":21,"no2":0,"co":86,"o3":69},{"time":1396207200,"so2":7,"part":22,"no2":0,"co":86,"o3":69},{"time":1396207800,"so2":6,"part":22,"no2":0,"co":99,"o3":70},{"time":1396208400,"so2":7,"part":22,"no2":0,"co":122,"o3":60},{"time":1396209000,"so2":7,"part":22,"no2":0,"co":134,"o3":64},{"time":1396209600,"so2":7,"part":22,"no2":0,"co":118,"o3":66},{"time":1396210200,"so2":7,"part":24,"no2":0,"co":89,"o3":67},{"time":1396210800,"so2":6,"part":25,"no2":0,"co":90,"o3":67},{"time":1396211400,"so2":6,"part":25,"no2":0,"co":94,"o3":64},{"time":1396212000,"so2":7,"part":25,"no2":0,"co":90,"o3":66},{"time":1396212600,"so2":7,"part":25,"no2":0,"co":133,"o3":61},{"time":1396213200,"so2":7,"part":25,"no2":0,"co":134,"o3":57},{"time":1396213800,"so2":7,"part":20,"no2":0,"co":141,"o3":59},{"time":1396214400,"so2":7,"part":20,"no2":0,"co":173,"o3":61},{"time":1396215000,"so2":8,"part":20,"no2":0,"co":182,"o3":64},{"time":1396215600,"so2":6,"part":20,"no2":0,"co":115,"o3":63},{"time":1396216200,"so2":6,"part":20,"no2":0,"co":92,"o3":62},{"time":1396216800,"so2":6,"part":20,"no2":0,"co":90,"o3":64}]}},{"t":"MALAGA","s":"CARRANQUE","so2":2,"co":2,"no2":2,"part":2,"o3":3,"g":3,"prev":3,"act":3,"evol":1,"gs":{"p":"MALAGA","t":"MALAGA","s":"CARRANQUE","addr":"AVDA. SANTA ROSA DE LIMA S/N","gsd":[{"time":1396134600,"so2":10,"part":20,"no2":69,"co":679,"o3":6},{"time":1396135200,"so2":10,"part":22,"no2":75,"co":748,"o3":5},{"time":1396135800,"so2":10,"part":27,"no2":74,"co":713,"o3":5},{"time":1396136400,"so2":10,"part":37,"no2":73,"co":738,"o3":5},{"time":1396137000,"so2":11,"part":39,"no2":71,"co":744,"o3":6},{"time":1396137600,"so2":10,"part":40,"no2":71,"co":734,"o3":5},{"time":1396138200,"so2":11,"part":39,"no2":70,"co":719,"o3":5},{"time":1396138800,"so2":10,"part":34,"no2":63,"co":670,"o3":5},{"time":1396139400,"so2":10,"part":35,"no2":63,"co":634,"o3":5},{"time":1396140000,"so2":10,"part":44,"no2":68,"co":722,"o3":5},{"time":1396140600,"so2":10,"part":49,"no2":66,"co":664,"o3":4},{"time":1396141200,"so2":10,"part":48,"no2":65,"co":646,"o3":4},{"time":1396141800,"so2":10,"part":33,"no2":64,"co":644,"o3":4},{"time":1396142400,"so2":10,"part":25,"no2":64,"co":615,"o3":4},{"time":1396143000,"so2":10,"part":26,"no2":62,"co":616,"o3":4},{"time":1396143600,"so2":10,"part":32,"no2":58,"co":570,"o3":5},{"time":1396144200,"so2":10,"part":23,"no2":59,"co":579,"o3":5},{"time":1396144800,"so2":10,"part":19,"no2":58,"co":579,"o3":4},{"time":1396145400,"so2":10,"part":17,"no2":53,"co":512,"o3":12},{"time":1396146000,"so2":9,"part":20,"no2":51,"co":506,"o3":14},{"time":1396146600,"so2":10,"part":17,"no2":39,"co":463,"o3":27},{"time":1396147200,"so2":10,"part":17,"no2":23,"co":413,"o3":47},{"time":1396147800,"so2":10,"part":8,"no2":20,"co":401,"o3":50},{"time":1396148400,"so2":9,"part":5,"no2":22,"co":426,"o3":45},{"time":1396149000,"so2":10,"part":5,"no2":41,"co":463,"o3":29},{"time":1396149600,"so2":10,"part":5,"no2":62,"co":603,"o3":4},{"time":1396150200,"so2":10,"part":13,"no2":52,"co":516,"o3":8},{"time":1396150800,"so2":10,"part":16,"no2":41,"co":478,"o3":19},{"time":1396151400,"so2":10,"part":19,"no2":38,"co":477,"o3":20},{"time":1396152000,"so2":9,"part":22,"no2":39,"co":465,"o3":14},{"time":1396152600,"so2":10,"part":21,"no2":45,"co":485,"o3":7},{"time":1396153200,"so2":10,"part":20,"no2":47,"co":460,"o3":7},{"time":1396153800,"so2":10,"part":23,"no2":50,"co":487,"o3":6},{"time":1396154400,"so2":10,"part":23,"no2":41,"co":457,"o3":12},{"time":1396155000,"so2":10,"part":21,"no2":26,"co":411,"o3":27},{"time":1396155600,"so2":10,"part":13,"no2":25,"co":404,"o3":30},{"time":1396156200,"so2":10,"part":17,"no2":18,"co":405,"o3":41},{"time":1396156800,"so2":10,"part":17,"no2":19,"co":395,"o3":43},{"time":1396157400,"so2":10,"part":7,"no2":32,"co":420,"o3":26},{"time":1396158000,"so2":10,"part":10,"no2":36,"co":423,"o3":22},{"time":1396158600,"so2":10,"part":7,"no2":33,"co":428,"o3":28},{"time":1396159200,"so2":10,"part":7,"no2":35,"co":417,"o3":26},{"time":1396159800,"so2":9,"part":9,"no2":25,"co":396,"o3":40},{"time":1396160400,"so2":10,"part":11,"no2":21,"co":383,"o3":45},{"time":1396161000,"so2":10,"part":12,"no2":20,"co":409,"o3":49},{"time":1396161600,"so2":10,"part":12,"no2":16,"co":389,"o3":58},{"time":1396162200,"so2":10,"part":8,"no2":11,"co":389,"o3":62},{"time":1396162800,"so2":9,"part":5,"no2":13,"co":379,"o3":59},{"time":1396163400,"so2":10,"part":5,"no2":21,"co":384,"o3":49},{"time":1396164000,"so2":10,"part":12,"no2":19,"co":378,"o3":48},{"time":1396164600,"so2":10,"part":6,"no2":19,"co":400,"o3":48},{"time":1396165200,"so2":10,"part":5,"no2":16,"co":387,"o3":51},{"time":1396165800,"so2":10,"part":5,"no2":23,"co":392,"o3":43},{"time":1396166400,"so2":10,"part":5,"no2":19,"co":366,"o3":46},{"time":1396167000,"so2":9,"part":9,"no2":17,"co":399,"o3":50},{"time":1396167600,"so2":10,"part":5,"no2":17,"co":393,"o3":51},{"time":1396168200,"so2":9,"part":5,"no2":16,"co":396,"o3":56},{"time":1396168800,"so2":10,"part":5,"no2":16,"co":388,"o3":56},{"time":1396169400,"so2":10,"part":10,"no2":15,"co":397,"o3":60},{"time":1396170000,"so2":10,"part":12,"no2":15,"co":402,"o3":63},{"time":1396170600,"so2":10,"part":6,"no2":17,"co":384,"o3":59},{"time":1396171200,"so2":10,"part":6,"no2":16,"co":393,"o3":63},{"time":1396171800,"so2":10,"part":8,"no2":15,"co":409,"o3":65},{"time":1396172400,"so2":9,"part":9,"no2":14,"co":391,"o3":68},{"time":1396173000,"so2":10,"part":5,"no2":13,"co":409,"o3":65},{"time":1396173600,"so2":10,"part":5,"no2":10,"co":395,"o3":77},{"time":1396174200,"so2":10,"part":5,"no2":10,"co":379,"o3":80},{"time":1396174800,"so2":10,"part":5,"no2":10,"co":394,"o3":83},{"time":1396175400,"so2":9,"part":5,"no2":6,"co":360,"o3":98},{"time":1396176000,"so2":10,"part":5,"no2":6,"co":355,"o3":99},{"time":1396176600,"so2":10,"part":5,"no2":7,"co":374,"o3":95},{"time":1396177200,"so2":10,"part":5,"no2":6,"co":385,"o3":96},{"time":1396177800,"so2":10,"part":5,"no2":5,"co":358,"o3":97},{"time":1396178400,"so2":10,"part":5,"no2":5,"co":362,"o3":98},{"time":1396179000,"so2":9,"part":5,"no2":6,"co":374,"o3":96},{"time":1396179600,"so2":10,"part":5,"no2":6,"co":390,"o3":94},{"time":1396180200,"so2":10,"part":10,"no2":6,"co":387,"o3":95},{"time":1396180800,"so2":10,"part":34,"no2":6,"co":366,"o3":96},{"time":1396181400,"so2":9,"part":23,"no2":4,"co":369,"o3":99},{"time":1396182000,"so2":9,"part":5,"no2":6,"co":365,"o3":97},{"time":1396182600,"so2":10,"part":5,"no2":6,"co":375,"o3":96},{"time":1396183200,"so2":10,"part":10,"no2":5,"co":378,"o3":96},{"time":1396183800,"so2":10,"part":15,"no2":7,"co":367,"o3":94},{"time":1396184400,"so2":10,"part":13,"no2":4,"co":357,"o3":97},{"time":1396185000,"so2":9,"part":5,"no2":6,"co":371,"o3":96},{"time":1396185600,"so2":10,"part":5,"no2":6,"co":363,"o3":97},{"time":1396186200,"so2":10,"part":5,"no2":6,"co":367,"o3":98},{"time":1396186800,"so2":10,"part":5,"no2":6,"co":348,"o3":97},{"time":1396187400,"so2":9,"part":10,"no2":10,"co":380,"o3":93},{"time":1396188000,"so2":9,"part":31,"no2":13,"co":404,"o3":91},{"time":1396188600,"so2":10,"part":23,"no2":12,"co":400,"o3":92},{"time":1396189200,"so2":10,"part":17,"no2":13,"co":384,"o3":93},{"time":1396189800,"so2":10,"part":16,"no2":11,"co":379,"o3":95},{"time":1396190400,"so2":10,"part":19,"no2":10,"co":388,"o3":95},{"time":1396191000,"so2":10,"part":19,"no2":12,"co":398,"o3":94},{"time":1396191600,"so2":10,"part":17,"no2":11,"co":371,"o3":96},{"time":1396192200,"so2":11,"part":11,"no2":11,"co":373,"o3":94},{"time":1396192800,"so2":11,"part":18,"no2":16,"co":387,"o3":88},{"time":1396193400,"so2":11,"part":19,"no2":15,"co":383,"o3":89},{"time":1396194000,"so2":10,"part":11,"no2":12,"co":388,"o3":91},{"time":1396194600,"so2":11,"part":7,"no2":11,"co":397,"o3":93},{"time":1396195200,"so2":11,"part":6,"no2":13,"co":401,"o3":91},{"time":1396195800,"so2":10,"part":28,"no2":15,"co":405,"o3":88},{"time":1396196400,"so2":10,"part":34,"no2":13,"co":406,"o3":89},{"time":1396197000,"so2":11,"part":14,"no2":10,"co":380,"o3":93},{"time":1396197600,"so2":10,"part":5,"no2":14,"co":373,"o3":88},{"time":1396198200,"so2":10,"part":5,"no2":12,"co":379,"o3":89},{"time":1396198800,"so2":10,"part":5,"no2":13,"co":394,"o3":88},{"time":1396199400,"so2":10,"part":9,"no2":14,"co":395,"o3":87},{"time":1396200000,"so2":10,"part":51,"no2":14,"co":384,"o3":86},{"time":1396200600,"so2":10,"part":30,"no2":13,"co":388,"o3":87},{"time":1396201200,"so2":10,"part":11,"no2":16,"co":394,"o3":84},{"time":1396201800,"so2":10,"part":13,"no2":16,"co":392,"o3":83},{"time":1396202400,"so2":10,"part":19,"no2":12,"co":390,"o3":86},{"time":1396203000,"so2":10,"part":21,"no2":16,"co":403,"o3":83},{"time":1396203600,"so2":10,"part":27,"no2":12,"co":382,"o3":87},{"time":1396204200,"so2":10,"part":29,"no2":9,"co":355,"o3":92},{"time":1396204800,"so2":10,"part":27,"no2":13,"co":382,"o3":88},{"time":1396205400,"so2":10,"part":23,"no2":13,"co":372,"o3":85},{"time":1396206000,"so2":10,"part":20,"no2":15,"co":387,"o3":79},{"time":1396206600,"so2":10,"part":22,"no2":24,"co":405,"o3":68},{"time":1396207200,"so2":10,"part":21,"no2":22,"co":401,"o3":69},{"time":1396207800,"so2":10,"part":14,"no2":19,"co":408,"o3":72},{"time":1396208400,"so2":10,"part":15,"no2":18,"co":404,"o3":73},{"time":1396209000,"so2":10,"part":20,"no2":18,"co":407,"o3":71},{"time":1396209600,"so2":10,"part":21,"no2":23,"co":414,"o3":66},{"time":1396210200,"so2":10,"part":16,"no2":33,"co":426,"o3":58},{"time":1396210800,"so2":10,"part":17,"no2":34,"co":449,"o3":54},{"time":1396211400,"so2":10,"part":19,"no2":43,"co":468,"o3":45},{"time":1396212000,"so2":10,"part":19,"no2":50,"co":471,"o3":39},{"time":1396212600,"so2":10,"part":22,"no2":37,"co":455,"o3":48},{"time":1396213200,"so2":10,"part":20,"no2":55,"co":500,"o3":34},{"time":1396213800,"so2":9,"part":20,"no2":37,"co":425,"o3":52},{"time":1396214400,"so2":10,"part":18,"no2":23,"co":405,"o3":66},{"time":1396215000,"so2":10,"part":14,"no2":16,"co":394,"o3":72},{"time":1396215600,"so2":10,"part":14,"no2":18,"co":398,"o3":69},{"time":1396216200,"so2":10,"part":15,"no2":17,"co":390,"o3":70},{"time":1396216800,"so2":10,"part":15,"no2":16,"co":401,"o3":69}]}},{"t":"MALAGA","s":"EL ATABAL","so2":2,"co":2,"no2":2,"part":2,"o3":3,"g":3,"prev":3,"act":3,"evol":1,"gs":{"p":"MALAGA","t":"MALAGA","s":"EL ATABAL","addr":"POTABILIZADORA-DESALOBRADORA EMASA","gsd":[{"time":1396134600,"so2":7,"part":45,"no2":56,"co":369,"o3":11},{"time":1396135200,"so2":7,"part":53,"no2":51,"co":312,"o3":16},{"time":1396135800,"so2":7,"part":55,"no2":51,"co":325,"o3":14},{"time":1396136400,"so2":6,"part":49,"no2":54,"co":293,"o3":14},{"time":1396137000,"so2":6,"part":42,"no2":57,"co":317,"o3":11},{"time":1396137600,"so2":7,"part":36,"no2":58,"co":315,"o3":13},{"time":1396138200,"so2":7,"part":29,"no2":41,"co":257,"o3":36},{"time":1396138800,"so2":6,"part":24,"no2":21,"co":228,"o3":51},{"time":1396139400,"so2":7,"part":17,"no2":18,"co":243,"o3":48},{"time":1396140000,"so2":7,"part":11,"no2":18,"co":221,"o3":46},{"time":1396140600,"so2":7,"part":7,"no2":16,"co":199,"o3":56},{"time":1396141200,"so2":6,"part":12,"no2":17,"co":206,"o3":58},{"time":1396141800,"so2":6,"part":14,"no2":17,"co":247,"o3":51},{"time":1396142400,"so2":6,"part":15,"no2":29,"co":240,"o3":42},{"time":1396143000,"so2":6,"part":18,"no2":10,"co":188,"o3":70},{"time":1396143600,"so2":7,"part":19,"no2":7,"co":174,"o3":68},{"time":1396144200,"so2":7,"part":17,"no2":11,"co":175,"o3":61},{"time":1396144800,"so2":7,"part":14,"no2":12,"co":194,"o3":60},{"time":1396145400,"so2":7,"part":10,"no2":26,"co":258,"o3":34},{"time":1396146000,"so2":6,"part":6,"no2":36,"co":262,"o3":28},{"time":1396146600,"so2":6,"part":8,"no2":36,"co":246,"o3":29},{"time":1396147200,"so2":6,"part":9,"no2":32,"co":264,"o3":30},{"time":1396147800,"so2":7,"part":12,"no2":26,"co":255,"o3":39},{"time":1396148400,"so2":7,"part":18,"no2":19,"co":229,"o3":50},{"time":1396149000,"so2":7,"part":21,"no2":15,"co":188,"o3":55},{"time":1396149600,"so2":6,"part":19,"no2":13,"co":199,"o3":54},{"time":1396150200,"so2":6,"part":16,"no2":14,"co":193,"o3":47},{"time":1396150800,"so2":6,"part":15,"no2":19,"co":195,"o3":41},{"time":1396151400,"so2":6,"part":14,"no2":14,"co":196,"o3":48},{"time":1396152000,"so2":6,"part":13,"no2":11,"co":188,"o3":57},{"time":1396152600,"so2":5,"part":10,"no2":7,"co":185,"o3":68},{"time":1396153200,"so2":6,"part":5,"no2":6,"co":167,"o3":68},{"time":1396153800,"so2":6,"part":3,"no2":7,"co":164,"o3":62},{"time":1396154400,"so2":6,"part":0,"no2":14,"co":174,"o3":60},{"time":1396155000,"so2":6,"part":0,"no2":14,"co":183,"o3":64},{"time":1396155600,"so2":6,"part":0,"no2":13,"co":183,"o3":62},{"time":1396156200,"so2":6,"part":0,"no2":13,"co":166,"o3":69},{"time":1396156800,"so2":6,"part":0,"no2":9,"co":159,"o3":67},{"time":1396157400,"so2":6,"part":0,"no2":6,"co":165,"o3":71},{"time":1396158000,"so2":6,"part":0,"no2":6,"co":167,"o3":66},{"time":1396158600,"so2":6,"part":1,"no2":9,"co":165,"o3":68},{"time":1396159200,"so2":6,"part":4,"no2":8,"co":178,"o3":64},{"time":1396159800,"so2":6,"part":7,"no2":14,"co":162,"o3":63},{"time":1396160400,"so2":6,"part":7,"no2":12,"co":190,"o3":57},{"time":1396161000,"so2":6,"part":7,"no2":10,"co":167,"o3":57},{"time":1396161600,"so2":6,"part":10,"no2":10,"co":198,"o3":56},{"time":1396162200,"so2":6,"part":12,"no2":11,"co":176,"o3":58},{"time":1396162800,"so2":5,"part":11,"no2":9,"co":175,"o3":57},{"time":1396163400,"so2":6,"part":7,"no2":9,"co":188,"o3":59},{"time":1396164000,"so2":6,"part":1,"no2":14,"co":187,"o3":62},{"time":1396164600,"so2":6,"part":0,"no2":10,"co":180,"o3":66},{"time":1396165200,"so2":6,"part":0,"no2":9,"co":195,"o3":66},{"time":1396165800,"so2":6,"part":0,"no2":10,"co":173,"o3":65},{"time":1396166400,"so2":6,"part":0,"no2":8,"co":193,"o3":79},{"time":1396167000,"so2":6,"part":0,"no2":6,"co":174,"o3":83},{"time":1396167600,"so2":6,"part":0,"no2":7,"co":162,"o3":88},{"time":1396168200,"so2":6,"part":0,"no2":4,"co":145,"o3":96},{"time":1396168800,"so2":6,"part":0,"no2":4,"co":172,"o3":83},{"time":1396169400,"so2":6,"part":0,"no2":7,"co":168,"o3":71},{"time":1396170000,"so2":6,"part":0,"no2":7,"co":157,"o3":82},{"time":1396170600,"so2":6,"part":0,"no2":0,"co":162,"o3":99},{"time":1396171200,"so2":6,"part":0,"no2":0,"co":165,"o3":105},{"time":1396171800,"so2":6,"part":0,"no2":0,"co":166,"o3":105},{"time":1396172400,"so2":6,"part":0,"no2":0,"co":158,"o3":104},{"time":1396173000,"so2":6,"part":0,"no2":0,"co":164,"o3":103},{"time":1396173600,"so2":6,"part":0,"no2":0,"co":156,"o3":105},{"time":1396174200,"so2":6,"part":0,"no2":0,"co":147,"o3":104},{"time":1396174800,"so2":6,"part":0,"no2":0,"co":159,"o3":104},{"time":1396175400,"so2":5,"part":0,"no2":0,"co":158,"o3":102},{"time":1396176000,"so2":6,"part":0,"no2":0,"co":156,"o3":103},{"time":1396176600,"so2":5,"part":0,"no2":0,"co":151,"o3":104},{"time":1396177200,"so2":6,"part":0,"no2":0,"co":144,"o3":103},{"time":1396177800,"so2":6,"part":0,"no2":0,"co":149,"o3":105},{"time":1396178400,"so2":6,"part":0,"no2":0,"co":159,"o3":105},{"time":1396179000,"so2":6,"part":0,"no2":0,"co":161,"o3":104},{"time":1396179600,"so2":6,"part":0,"no2":0,"co":164,"o3":103},{"time":1396180200,"so2":6,"part":4,"no2":0,"co":166,"o3":102},{"time":1396180800,"so2":6,"part":8,"no2":0,"co":149,"o3":103},{"time":1396181400,"so2":5,"part":5,"no2":0,"co":155,"o3":103},{"time":1396182000,"so2":5,"part":4,"no2":0,"co":156,"o3":104},{"time":1396182600,"so2":5,"part":1,"no2":0,"co":159,"o3":105},{"time":1396183200,"so2":6,"part":0,"no2":0,"co":163,"o3":104},{"time":1396183800,"so2":6,"part":0,"no2":0,"co":149,"o3":105},{"time":1396184400,"so2":6,"part":0,"no2":0,"co":161,"o3":105},{"time":1396185000,"so2":6,"part":0,"no2":6,"co":163,"o3":103},{"time":1396185600,"so2":6,"part":3,"no2":4,"co":165,"o3":106},{"time":1396186200,"so2":6,"part":9,"no2":4,"co":168,"o3":106},{"time":1396186800,"so2":6,"part":11,"no2":4,"co":156,"o3":107},{"time":1396187400,"so2":5,"part":12,"no2":3,"co":156,"o3":107},{"time":1396188000,"so2":6,"part":9,"no2":3,"co":176,"o3":104},{"time":1396188600,"so2":6,"part":7,"no2":7,"co":187,"o3":101},{"time":1396189200,"so2":6,"part":9,"no2":7,"co":161,"o3":101},{"time":1396189800,"so2":6,"part":8,"no2":5,"co":158,"o3":104},{"time":1396190400,"so2":6,"part":8,"no2":5,"co":181,"o3":102},{"time":1396191000,"so2":6,"part":7,"no2":9,"co":186,"o3":101},{"time":1396191600,"so2":7,"part":9,"no2":5,"co":165,"o3":103},{"time":1396192200,"so2":6,"part":13,"no2":7,"co":170,"o3":103},{"time":1396192800,"so2":6,"part":16,"no2":5,"co":160,"o3":103},{"time":1396193400,"so2":6,"part":13,"no2":6,"co":152,"o3":101},{"time":1396194000,"so2":6,"part":12,"no2":7,"co":165,"o3":100},{"time":1396194600,"so2":6,"part":14,"no2":9,"co":181,"o3":97},{"time":1396195200,"so2":6,"part":10,"no2":8,"co":162,"o3":99},{"time":1396195800,"so2":6,"part":7,"no2":11,"co":175,"o3":92},{"time":1396196400,"so2":7,"part":8,"no2":11,"co":164,"o3":95},{"time":1396197000,"so2":7,"part":8,"no2":11,"co":168,"o3":95},{"time":1396197600,"so2":6,"part":12,"no2":9,"co":172,"o3":99},{"time":1396198200,"so2":6,"part":16,"no2":6,"co":160,"o3":100},{"time":1396198800,"so2":6,"part":18,"no2":8,"co":179,"o3":98},{"time":1396199400,"so2":6,"part":19,"no2":7,"co":158,"o3":98},{"time":1396200000,"so2":5,"part":21,"no2":7,"co":154,"o3":97},{"time":1396200600,"so2":6,"part":21,"no2":3,"co":159,"o3":100},{"time":1396201200,"so2":5,"part":19,"no2":4,"co":152,"o3":97},{"time":1396201800,"so2":5,"part":18,"no2":9,"co":181,"o3":89},{"time":1396202400,"so2":6,"part":19,"no2":10,"co":172,"o3":88},{"time":1396203000,"so2":5,"part":20,"no2":9,"co":167,"o3":87},{"time":1396203600,"so2":6,"part":23,"no2":9,"co":173,"o3":86},{"time":1396204200,"so2":6,"part":28,"no2":8,"co":166,"o3":90},{"time":1396204800,"so2":6,"part":28,"no2":14,"co":182,"o3":80},{"time":1396205400,"so2":6,"part":28,"no2":9,"co":160,"o3":84},{"time":1396206000,"so2":6,"part":29,"no2":10,"co":183,"o3":83},{"time":1396206600,"so2":6,"part":30,"no2":13,"co":187,"o3":76},{"time":1396207200,"so2":5,"part":27,"no2":13,"co":164,"o3":80},{"time":1396207800,"so2":6,"part":25,"no2":12,"co":165,"o3":74},{"time":1396208400,"so2":6,"part":24,"no2":11,"co":162,"o3":73},{"time":1396209000,"so2":5,"part":25,"no2":10,"co":163,"o3":75},{"time":1396209600,"so2":5,"part":28,"no2":13,"co":177,"o3":73},{"time":1396210200,"so2":6,"part":29,"no2":10,"co":175,"o3":82},{"time":1396210800,"so2":6,"part":25,"no2":8,"co":174,"o3":83},{"time":1396211400,"so2":5,"part":21,"no2":9,"co":165,"o3":84},{"time":1396212000,"so2":5,"part":18,"no2":6,"co":163,"o3":84},{"time":1396212600,"so2":5,"part":16,"no2":6,"co":160,"o3":83},{"time":1396213200,"so2":5,"part":11,"no2":10,"co":178,"o3":77},{"time":1396213800,"so2":5,"part":9,"no2":8,"co":166,"o3":84},{"time":1396214400,"so2":5,"part":8,"no2":7,"co":141,"o3":83},{"time":1396215000,"so2":5,"part":12,"no2":7,"co":158,"o3":80},{"time":1396215600,"so2":5,"part":17,"no2":8,"co":152,"o3":79},{"time":1396216200,"so2":5,"part":18,"no2":7,"co":147,"o3":81},{"time":1396216800,"so2":6,"part":18,"no2":6,"co":155,"o3":83}]}},{"t":"MARBELLA","s":"MARBELLA ARCO","so2":2,"co":2,"no2":2,"part":2,"o3":3,"g":3,"prev":3,"act":3,"evol":1,"gs":{"p":"MALAGA","t":"MARBELLA","s":"MARBELLA ARCO","addr":"N-340 S/N","gsd":[{"time":1396134600,"so2":7,"part":17,"no2":27,"co":408,"o3":68},{"time":1396135200,"so2":7,"part":16,"no2":23,"co":450,"o3":69},{"time":1396135800,"so2":7,"part":16,"no2":19,"co":402,"o3":71},{"time":1396136400,"so2":7,"part":15,"no2":16,"co":403,"o3":72},{"time":1396137000,"so2":6,"part":16,"no2":17,"co":403,"o3":63},{"time":1396137600,"so2":6,"part":17,"no2":21,"co":427,"o3":51},{"time":1396138200,"so2":6,"part":24,"no2":23,"co":479,"o3":43},{"time":1396138800,"so2":6,"part":22,"no2":26,"co":465,"o3":38},{"time":1396139400,"so2":6,"part":31,"no2":26,"co":459,"o3":43},{"time":1396140000,"so2":6,"part":16,"no2":25,"co":429,"o3":50},{"time":1396140600,"so2":6,"part":15,"no2":27,"co":464,"o3":46},{"time":1396141200,"so2":6,"part":18,"no2":18,"co":483,"o3":52},{"time":1396141800,"so2":6,"part":18,"no2":19,"co":466,"o3":54},{"time":1396142400,"so2":5,"part":18,"no2":9,"co":415,"o3":71},{"time":1396143000,"so2":6,"part":17,"no2":9,"co":461,"o3":64},{"time":1396143600,"so2":6,"part":14,"no2":15,"co":450,"o3":58},{"time":1396144200,"so2":6,"part":14,"no2":16,"co":426,"o3":51},{"time":1396144800,"so2":6,"part":16,"no2":21,"co":615,"o3":40},{"time":1396145400,"so2":6,"part":16,"no2":18,"co":453,"o3":46},{"time":1396146000,"so2":6,"part":15,"no2":16,"co":377,"o3":46},{"time":1396146600,"so2":6,"part":14,"no2":19,"co":415,"o3":40},{"time":1396147200,"so2":6,"part":14,"no2":14,"co":421,"o3":33},{"time":1396147800,"so2":6,"part":13,"no2":17,"co":419,"o3":31},{"time":1396148400,"so2":6,"part":12,"no2":23,"co":432,"o3":31},{"time":1396149000,"so2":6,"part":12,"no2":21,"co":407,"o3":26},{"time":1396149600,"so2":5,"part":11,"no2":20,"co":391,"o3":34},{"time":1396150200,"so2":6,"part":11,"no2":20,"co":417,"o3":37},{"time":1396150800,"so2":6,"part":11,"no2":25,"co":430,"o3":25},{"time":1396151400,"so2":6,"part":11,"no2":22,"co":403,"o3":25},{"time":1396152000,"so2":6,"part":10,"no2":23,"co":398,"o3":22},{"time":1396152600,"so2":6,"part":9,"no2":19,"co":357,"o3":33},{"time":1396153200,"so2":5,"part":8,"no2":17,"co":368,"o3":31},{"time":1396153800,"so2":6,"part":7,"no2":14,"co":352,"o3":35},{"time":1396154400,"so2":6,"part":7,"no2":20,"co":344,"o3":29},{"time":1396155000,"so2":7,"part":7,"no2":17,"co":352,"o3":30},{"time":1396155600,"so2":6,"part":7,"no2":19,"co":357,"o3":31},{"time":1396156200,"so2":6,"part":7,"no2":18,"co":361,"o3":35},{"time":1396156800,"so2":7,"part":7,"no2":21,"co":359,"o3":45},{"time":1396157400,"so2":6,"part":7,"no2":13,"co":356,"o3":54},{"time":1396158000,"so2":6,"part":7,"no2":14,"co":381,"o3":55},{"time":1396158600,"so2":6,"part":7,"no2":14,"co":389,"o3":49},{"time":1396159200,"so2":6,"part":7,"no2":27,"co":397,"o3":32},{"time":1396159800,"so2":6,"part":8,"no2":40,"co":359,"o3":11},{"time":1396160400,"so2":6,"part":9,"no2":53,"co":357,"o3":9},{"time":1396161000,"so2":7,"part":10,"no2":50,"co":358,"o3":10},{"time":1396161600,"so2":5,"part":10,"no2":45,"co":369,"o3":16},{"time":1396162200,"so2":6,"part":8,"no2":35,"co":372,"o3":35},{"time":1396162800,"so2":6,"part":12,"no2":54,"co":483,"o3":18},{"time":1396163400,"so2":7,"part":18,"no2":60,"co":491,"o3":13},{"time":1396164000,"so2":6,"part":12,"no2":46,"co":411,"o3":24},{"time":1396164600,"so2":6,"part":11,"no2":44,"co":505,"o3":27},{"time":1396165200,"so2":6,"part":11,"no2":46,"co":488,"o3":32},{"time":1396165800,"so2":6,"part":8,"no2":33,"co":403,"o3":48},{"time":1396166400,"so2":6,"part":10,"no2":15,"co":434,"o3":63},{"time":1396167000,"so2":6,"part":8,"no2":13,"co":374,"o3":65},{"time":1396167600,"so2":5,"part":7,"no2":9,"co":374,"o3":70},{"time":1396168200,"so2":6,"part":7,"no2":5,"co":387,"o3":75},{"time":1396168800,"so2":6,"part":7,"no2":9,"co":461,"o3":73},{"time":1396169400,"so2":6,"part":6,"no2":10,"co":413,"o3":73},{"time":1396170000,"so2":5,"part":5,"no2":9,"co":423,"o3":77},{"time":1396170600,"so2":6,"part":6,"no2":9,"co":388,"o3":74},{"time":1396171200,"so2":6,"part":5,"no2":7,"co":381,"o3":80},{"time":1396171800,"so2":6,"part":5,"no2":4,"co":403,"o3":82},{"time":1396172400,"so2":6,"part":6,"no2":7,"co":390,"o3":83},{"time":1396173000,"so2":7,"part":7,"no2":9,"co":367,"o3":84},{"time":1396173600,"so2":6,"part":8,"no2":5,"co":403,"o3":85},{"time":1396174200,"so2":6,"part":8,"no2":5,"co":389,"o3":84},{"time":1396174800,"so2":6,"part":10,"no2":6,"co":401,"o3":84},{"time":1396175400,"so2":5,"part":10,"no2":4,"co":412,"o3":86},{"time":1396176000,"so2":6,"part":10,"no2":5,"co":390,"o3":86},{"time":1396176600,"so2":6,"part":11,"no2":4,"co":434,"o3":89},{"time":1396177200,"so2":6,"part":11,"no2":4,"co":409,"o3":91},{"time":1396177800,"so2":5,"part":11,"no2":6,"co":408,"o3":89},{"time":1396178400,"so2":6,"part":13,"no2":14,"co":424,"o3":85},{"time":1396179000,"so2":5,"part":12,"no2":8,"co":432,"o3":91},{"time":1396179600,"so2":5,"part":14,"no2":5,"co":414,"o3":91},{"time":1396180200,"so2":6,"part":17,"no2":5,"co":399,"o3":91},{"time":1396180800,"so2":6,"part":18,"no2":6,"co":456,"o3":95},{"time":1396181400,"so2":6,"part":19,"no2":9,"co":461,"o3":89},{"time":1396182000,"so2":5,"part":16,"no2":11,"co":462,"o3":89},{"time":1396182600,"so2":6,"part":16,"no2":11,"co":450,"o3":89},{"time":1396183200,"so2":6,"part":15,"no2":13,"co":450,"o3":87},{"time":1396183800,"so2":6,"part":16,"no2":13,"co":469,"o3":85},{"time":1396184400,"so2":7,"part":15,"no2":13,"co":444,"o3":87},{"time":1396185000,"so2":6,"part":16,"no2":10,"co":437,"o3":91},{"time":1396185600,"so2":7,"part":17,"no2":8,"co":425,"o3":91},{"time":1396186200,"so2":6,"part":15,"no2":6,"co":419,"o3":91},{"time":1396186800,"so2":6,"part":13,"no2":5,"co":392,"o3":92},{"time":1396187400,"so2":7,"part":13,"no2":3,"co":425,"o3":93},{"time":1396188000,"so2":6,"part":12,"no2":4,"co":431,"o3":92},{"time":1396188600,"so2":6,"part":13,"no2":4,"co":410,"o3":94},{"time":1396189200,"so2":6,"part":12,"no2":3,"co":431,"o3":94},{"time":1396189800,"so2":6,"part":21,"no2":7,"co":441,"o3":88},{"time":1396190400,"so2":6,"part":18,"no2":11,"co":434,"o3":85},{"time":1396191000,"so2":6,"part":16,"no2":10,"co":448,"o3":88},{"time":1396191600,"so2":7,"part":16,"no2":8,"co":459,"o3":90},{"time":1396192200,"so2":6,"part":19,"no2":8,"co":444,"o3":91},{"time":1396192800,"so2":6,"part":21,"no2":8,"co":425,"o3":89},{"time":1396193400,"so2":6,"part":21,"no2":9,"co":457,"o3":90},{"time":1396194000,"so2":6,"part":21,"no2":9,"co":420,"o3":91},{"time":1396194600,"so2":7,"part":22,"no2":7,"co":431,"o3":91},{"time":1396195200,"so2":6,"part":23,"no2":6,"co":441,"o3":91},{"time":1396195800,"so2":7,"part":25,"no2":8,"co":455,"o3":88},{"time":1396196400,"so2":6,"part":24,"no2":8,"co":439,"o3":90},{"time":1396197000,"so2":6,"part":18,"no2":4,"co":433,"o3":90},{"time":1396197600,"so2":7,"part":16,"no2":5,"co":390,"o3":91},{"time":1396198200,"so2":6,"part":19,"no2":3,"co":368,"o3":90},{"time":1396198800,"so2":6,"part":18,"no2":4,"co":407,"o3":88},{"time":1396199400,"so2":6,"part":18,"no2":6,"co":411,"o3":84},{"time":1396200000,"so2":7,"part":16,"no2":5,"co":365,"o3":88},{"time":1396200600,"so2":6,"part":17,"no2":3,"co":377,"o3":88},{"time":1396201200,"so2":6,"part":17,"no2":4,"co":358,"o3":84},{"time":1396201800,"so2":7,"part":20,"no2":8,"co":396,"o3":85},{"time":1396202400,"so2":6,"part":21,"no2":7,"co":407,"o3":86},{"time":1396203000,"so2":6,"part":23,"no2":5,"co":404,"o3":87},{"time":1396203600,"so2":6,"part":25,"no2":12,"co":415,"o3":88},{"time":1396204200,"so2":6,"part":27,"no2":5,"co":399,"o3":90},{"time":1396204800,"so2":6,"part":26,"no2":7,"co":396,"o3":87},{"time":1396205400,"so2":6,"part":17,"no2":14,"co":400,"o3":80},{"time":1396206000,"so2":6,"part":19,"no2":13,"co":413,"o3":81},{"time":1396206600,"so2":5,"part":16,"no2":25,"co":455,"o3":66},{"time":1396207200,"so2":6,"part":18,"no2":25,"co":437,"o3":71},{"time":1396207800,"so2":7,"part":19,"no2":12,"co":363,"o3":84},{"time":1396208400,"so2":6,"part":20,"no2":7,"co":364,"o3":85},{"time":1396209000,"so2":6,"part":22,"no2":14,"co":385,"o3":77},{"time":1396209600,"so2":7,"part":21,"no2":25,"co":493,"o3":68},{"time":1396210200,"so2":6,"part":19,"no2":22,"co":503,"o3":68},{"time":1396210800,"so2":6,"part":17,"no2":26,"co":482,"o3":65},{"time":1396211400,"so2":6,"part":13,"no2":21,"co":426,"o3":70},{"time":1396212000,"so2":6,"part":15,"no2":21,"co":424,"o3":69},{"time":1396212600,"so2":6,"part":13,"no2":25,"co":431,"o3":66},{"time":1396213200,"so2":6,"part":11,"no2":14,"co":396,"o3":78},{"time":1396213800,"so2":6,"part":13,"no2":13,"co":437,"o3":74},{"time":1396214400,"so2":6,"part":17,"no2":20,"co":427,"o3":71},{"time":1396215000,"so2":7,"part":15,"no2":7,"co":381,"o3":81},{"time":1396215600,"so2":6,"part":15,"no2":6,"co":398,"o3":81},{"time":1396216200,"so2":6,"part":16,"no2":4,"co":378,"o3":82},{"time":1396216800,"so2":6,"part":18,"no2":15,"co":422,"o3":73}]}}]}